{
  "html": "<body style=\"background-color:#F0F8FF; font-family:Verdana, Arial, Helvetica, sans-serif; font-size:12; color:#000000; \">\r\n<span style=\"font-size:25px;\">Fujitsu AAA HR-4UTC 750mAh (White)</span><br>\r\n<br>\r\n<img src=\"https://lygte-info.dk/pic/Batteries2013NiMH/Fujitsu%20AAA%20HR-4UTC%20750mAh%20(White)/DSC_8332.jpg\" border=\"0\" alt=\"DSC_8332\"><br>\r\n<br>\r\nOfficial specifications:<ul>\r\n<li>Nominal voltage: 1.2V\r\n</li><li>Typical capacity: 800mAh\r\n</li><li>Minimum capacity: 750mAh\r\n</li><li>Low self discharge (LSD)\r\n</li><li>Retains 85% charge after one year, 70% after 5 years.\r\n</li><li>Rechargeable up to 2100 times. \r\n</li></ul>\r\n<img src=\"https://lygte-info.dk/pic/Batteries2013NiMH/Fujitsu%20AAA%20HR-4UTC%20750mAh%20(White)/Fujitsu%20AAA%20HR-4UTC%20750mAh%20(White)-info.png\" border=\"0\" alt=\"Fujitsu%20AAA%20HR-4UTC%20750mAh%20(White)-info\"><br>\r\nMaximum temperature raise at different discharge currents: 1A:+1,9\u00b0C, 2A:+4,5\u00b0C, 3A:+6,7\u00b0C, 5A:+10,5\u00b0<br>\r\nThese cells are long life NiMH from the FDK factory in Japan.<br>\r\n<br>\r\n<a href=\"https://lygte-info.dk/pic/Batteries2013NiMH/Fujitsu%20AAA%20HR-4UTC%20750mAh%20(White)/DSC_8320a.jpg\"><img src=\"https://lygte-info.dk/pic/Batteries2013NiMH/Fujitsu%20AAA%20HR-4UTC%20750mAh%20(White)/DSC_8320.jpg\" border=\"0\" alt=\"DSC_8320\"></a> <a href=\"https://lygte-info.dk/pic/Batteries2013NiMH/Fujitsu%20AAA%20HR-4UTC%20750mAh%20(White)/DSC_8321a.jpg\"><img src=\"https://lygte-info.dk/pic/Batteries2013NiMH/Fujitsu%20AAA%20HR-4UTC%20750mAh%20(White)/DSC_8321.jpg\" border=\"0\" alt=\"DSC_8321\"></a><br>\r\n<br>\r\n<br>\r\n<img src=\"https://lygte-info.dk/pic/Batteries2013NiMH/Fujitsu%20AAA%20HR-4UTC%20750mAh%20(White)/DSC_8333.jpg\" border=\"0\" alt=\"DSC_8333\"> <img src=\"https://lygte-info.dk/pic/Batteries2013NiMH/Fujitsu%20AAA%20HR-4UTC%20750mAh%20(White)/DSC_8334.jpg\" border=\"0\" alt=\"DSC_8334\"><br>\r\n<br>\r\n<img src=\"https://lygte-info.dk/pic/Batteries2013NiMH/Fujitsu%20AAA%20HR-4UTC%20750mAh%20(White)/DSC_8335.jpg\" border=\"0\" alt=\"DSC_8335\"><br>\r\n<img src=\"https://lygte-info.dk/pic/Batteries2013NiMH/Fujitsu%20AAA%20HR-4UTC%20750mAh%20(White)/DSC_8336.jpg\" border=\"0\" alt=\"DSC_8336\"><br>\r\n<img src=\"https://lygte-info.dk/pic/Batteries2013NiMH/Fujitsu%20AAA%20HR-4UTC%20750mAh%20(White)/DSC_8337.jpg\" border=\"0\" alt=\"DSC_8337\"><br>\r\n<br>\r\n<br>\r\n<img src=\"https://lygte-info.dk/pic/Batteries2013NiMH/Fujitsu%20AAA%20HR-4UTC%20750mAh%20(White)/Fujitsu%20AAA%20HR-4UTC%20750mAh%20(White)-Capacity.png\" border=\"0\" alt=\"Fujitsu%20AAA%20HR-4UTC%20750mAh%20(White)-Capacity\"><br>\r\n<br>\r\nThere is very good tracking between the two cells. They can handle 5A current, but as usual it is better to use a lower current.<br>\r\n<br>\r\n<img src=\"https://lygte-info.dk/pic/Batteries2013NiMH/Fujitsu%20AAA%20HR-4UTC%20750mAh%20(White)/Fujitsu%20AAA%20HR-4UTC%20750mAh%20(White)-CapacityTime.png\" border=\"0\" alt=\"Fujitsu%20AAA%20HR-4UTC%20750mAh%20(White)-CapacityTime\"><br>\r\n<br>\r\n<img src=\"https://lygte-info.dk/pic/Batteries2013NiMH/Fujitsu%20AAA%20HR-4UTC%20750mAh%20(White)/Fujitsu%20AAA%20HR-4UTC%20750mAh%20(White)-CapacityTimeHours.png\" border=\"0\" alt=\"Fujitsu%20AAA%20HR-4UTC%20750mAh%20(White)-CapacityTimeHours\"><br>\r\n<br>\r\n<img src=\"https://lygte-info.dk/pic/Batteries2013NiMH/Fujitsu%20AAA%20HR-4UTC%20750mAh%20(White)/Fujitsu%20AAA%20HR-4UTC%20750mAh%20(White)-Energy.png\" border=\"0\" alt=\"Fujitsu%20AAA%20HR-4UTC%20750mAh%20(White)-Energy\"><br>\r\n<br>\r\n<img src=\"https://lygte-info.dk/pic/Batteries2013NiMH/Fujitsu%20AAA%20HR-4UTC%20750mAh%20(White)/Fujitsu%20AAA%20HR-4UTC%20750mAh%20(White)-PowerLoadTime.png\" border=\"0\" alt=\"Fujitsu%20AAA%20HR-4UTC%20750mAh%20(White)-PowerLoadTime\"><br>\r\n<br>\r\n<img src=\"https://lygte-info.dk/pic/Batteries2013NiMH/Fujitsu%20AAA%20HR-4UTC%20750mAh%20(White)/Fujitsu%20AAA%20HR-4UTC%20750mAh%20(White)-CurrentTest.png\" border=\"0\" alt=\"Fujitsu%20AAA%20HR-4UTC%20750mAh%20(White)-CurrentTest\"><br>\r\n<br>\r\n<img src=\"https://lygte-info.dk/pic/Batteries2013NiMH/Fujitsu%20AAA%20HR-4UTC%20750mAh%20(White)/Fujitsu%20AAA%20HR-4UTC%20750mAh%20(White)-Charge.png\" border=\"0\" alt=\"Fujitsu%20AAA%20HR-4UTC%20750mAh%20(White)-Charge\"><br>\r\n<br>\r\n<br>\r\n<br>\r\n<span style=\"font-size:25px;\">Conclusion</span><br>\r\n<br>\r\nThese cell has very good performance and are supposed to last for many years.<br>\r\n<br>\r\n<br>\r\n<br>\r\n<span style=\"font-size:25px;\">Notes and links</span><br>\r\n<br>\r\nThe batteries was supplied by FDK German for a review.<br>\r\n<br>\r\n<a href=\"https://lygte-info.dk/info/Batteries2012Info%20UK.html\">How is the test done and how to read the charts</a><br>\r\n<a href=\"https://lygte-info.dk/review/batteries2012/CommonAAcomparator.php\">Compare to other AA/AAA batteries: Alkaline/NiMH/Lithium</a><br>\r\n</body>",
  "_id": "fujitsu-aaa-hr-4utc-750mah-white",
  "title": "Fujitsu AAA HR-4UTC 750mAh (White)",
  "slug": "fujitsu-aaa-hr-4utc-750mah-white",
  "url": "https://lygte-info.dk/review/batteries2012/Fujitsu%20AAA%20HR-4UTC%20750mAh%20%28White%29%20UK.html",
  "type": "AAA",
  "year": 2020,
  "preview": "https://lygte-info.dk/pic/Batteries2013NiMH/Fujitsu%20AAA%20HR-4UTC%20750mAh%20(White)/DSC_8332.jpg"
}