{
  "html": "<body style=\"background-color:#F0F8FF; font-family:Verdana, Arial, Helvetica, sans-serif; font-size:12; color:#000000; \">\r\n<span style=\"font-size:25px;\">EagleTac 17650 1600mAh (Black)</span><br>\r\n<br>\r\n<img src=\"https://lygte-info.dk/pic/Batteries2012/EagleTac%2017650%201600mAh%20(Black)/DSC_0804.jpg\" border=\"0\" alt=\"DSC_0804\"><br>\r\n<br>\r\nOfficial specifications:<ul>\r\n<li>1600mAh IC PROTECTED Rechargeable Cell (takes the place of 2-R123 cells in some applications) (4.2V hot off charger)\r\n</li><li>Measures 67.6mm in height (+/-0.1mm) and 17mm in width\r\n</li><li>IC protected for a) over-charge, b) over-discharge, c) short circuit, d) current overflow of 3A+\r\n</li><li>True protrude top design, fits all flashlights\r\n</li><li>High discharge rate 3A+\r\n</li><li>Nominal voltage: 3.7V, charge up to 4.2V, use CC/CV charger to charge\r\n</li><li>Reinforced steel plate bottom, highly efficient protective PCB design\r\n</li><li>Packaged in individual box and anti-static bag\r\n</li></ul>\r\n<br>\r\n<img src=\"https://lygte-info.dk/pic/Batteries2012/EagleTac%2017650%201600mAh%20(Black)/EagleTac%2017650%201600mAh%20(Black)-info.png\" border=\"0\" alt=\"EagleTac%2017650%201600mAh%20(Black)-info\"><br>\r\n<br>\r\nThis battery has about the same size as two CR123 batteries (Diameter is slightly larger), but lower voltage. This makes it possible to use in instead of two CR123 batteries in most equipment, but the equipment might say \"low battery\".<br>\r\nThis size is also sometimes called 17670, i.e. 67 instead of 65.<br>\r\n<br>\r\n<img src=\"https://lygte-info.dk/pic/Batteries2012/EagleTac%2017650%201600mAh%20(Black)/DSC_0802.jpg\" border=\"0\" alt=\"DSC_0802\"> <img src=\"https://lygte-info.dk/pic/Batteries2012/EagleTac%2017650%201600mAh%20(Black)/DSC_0803.jpg\" border=\"0\" alt=\"DSC_0803\"><br>\r\n<br>\r\n<img src=\"https://lygte-info.dk/pic/Batteries2012/EagleTac%2017650%201600mAh%20(Black)/DSC_0807.jpg\" border=\"0\" alt=\"DSC_0807\"> <img src=\"https://lygte-info.dk/pic/Batteries2012/EagleTac%2017650%201600mAh%20(Black)/DSC_0808.jpg\" border=\"0\" alt=\"DSC_0808\"><br>\r\n<img src=\"https://lygte-info.dk/pic/Batteries2012/EagleTac%2017650%201600mAh%20(Black)/DSC_0805.jpg\" border=\"0\" alt=\"DSC_0805\"><br>\r\n<img src=\"https://lygte-info.dk/pic/Batteries2012/EagleTac%2017650%201600mAh%20(Black)/DSC_0806.jpg\" border=\"0\" alt=\"DSC_0806\"><br>\r\n<br>\r\n<img src=\"https://lygte-info.dk/pic/Batteries2012/EagleTac%2017650%201600mAh%20(Black)/EagleTac%2017650%201600mAh%20(Black)-Capacity.png\" border=\"0\" alt=\"EagleTac%2017650%201600mAh%20(Black)-Capacity\"><br>\r\n<br>\r\nThis size batteries does have a rather low capacity, when size permits it is much better to uses <b>18</b>650 instead of <b>17</b>650, that extra millimeter in diameter will nearly double the capacity. <br>\r\n<br>\r\n<img src=\"https://lygte-info.dk/pic/Batteries2012/EagleTac%2017650%201600mAh%20(Black)/EagleTac%2017650%201600mAh%20(Black)-CapacityTimeHours.png\" border=\"0\" alt=\"EagleTac%2017650%201600mAh%20(Black)-CapacityTimeHours\"><br>\r\n<br>\r\n<img src=\"https://lygte-info.dk/pic/Batteries2012/EagleTac%2017650%201600mAh%20(Black)/EagleTac%2017650%201600mAh%20(Black)-CapacityTime.png\" border=\"0\" alt=\"EagleTac%2017650%201600mAh%20(Black)-CapacityTime\"><br>\r\n<br>\r\n<img src=\"https://lygte-info.dk/pic/Batteries2012/EagleTac%2017650%201600mAh%20(Black)/EagleTac%2017650%201600mAh%20(Black)-Energy.png\" border=\"0\" alt=\"EagleTac%2017650%201600mAh%20(Black)-Energy\"><br>\r\n<br>\r\n<img src=\"https://lygte-info.dk/pic/Batteries2012/EagleTac%2017650%201600mAh%20(Black)/EagleTac%2017650%201600mAh%20(Black)-PowerLoadTime.png\" border=\"0\" alt=\"EagleTac%2017650%201600mAh%20(Black)-PowerLoadTime\"><br>\r\n<br>\r\n<img src=\"https://lygte-info.dk/pic/Batteries2012/EagleTac%2017650%201600mAh%20(Black)/EagleTac%2017650%201600mAh%20(Black)-TripCurrent.png\" border=\"0\" alt=\"EagleTac%2017650%201600mAh%20(Black)-TripCurrent\"><br>\r\n<br>\r\n<img src=\"https://lygte-info.dk/pic/Batteries2012/EagleTac%2017650%201600mAh%20(Black)/EagleTac%2017650%201600mAh%20(Black)-Charge.png\" border=\"0\" alt=\"EagleTac%2017650%201600mAh%20(Black)-Charge\"><br>\r\n<br>\r\n<br>\r\n<br>\r\n<span style=\"font-size:25px;\">Conclusion</span><br>\r\n<br>\r\nThe battery works perfectly and the construction looks acceptable, only minus I could find is that the cell is from a unspecified supplier. The low capacity is also a minus, but that is common for all 17650 batteries. <br>\r\nI will call it a good battery.<br>\r\n<br>\r\n<br>\r\n<br>\r\n<span style=\"font-size:25px;\">Notes and links</span><br>\r\n<br>\r\nThe batteries was supplied by IlluminationGear.com for review.<br>\r\n<br>\r\n<a href=\"https://lygte-info.dk/info/Batteries2012Info%20UK.html\">How is the test done and how to read the charts</a><br>\r\n<a href=\"https://lygte-info.dk/info/battery%20protection%20UK.html\">How is a protected LiIon battery constructed</a><br>\r\n<a href=\"https://lygte-info.dk/info/Battery%20button%20or%20flat%20UK.html\">More about button top and flat top batteries</a><br>\r\n</body>",
  "url": "https://lygte-info.dk/review/batteries2012/EagleTac 17650 1600mAh (Black) UK.html",
  "title": "EagleTac 17650 1600mAh (Black)",
  "slug": "eagletac-17650-1600mah-black",
  "battery_type": "LiIon",
  "top": "SB",
  "rated_mah": 1600,
  "prot": "5.8",
  "year": "1-2012",
  "preview": "https://lygte-info.dk/pic/Batteries2012/EagleTac%2017650%201600mAh%20(Black)/DSC_0804.jpg"
}