{
  "html": "<body style=\"background-color:#F0F8FF; font-family:Verdana, Arial, Helvetica, sans-serif; font-size:12; color:#000000; \">\r\n<span style=\"font-size:25px;\">Staring IMR18650 2500mAh (Green)</span><br>\r\n<br>\r\n<img src=\"https://lygte-info.dk/pic/Batteries2012/Staring%20IMR18650%202500mAh%20(Green)/DSC_6654.jpg\" border=\"0\" alt=\"DSC_6654\"><br>\r\n<br>\r\nOfficial specifications:<ul>\r\n<li>Battery type: 18650 battery\r\n</li><li>Typical capacity: 2500mAh (real capacity)\r\n</li><li>Typical voltage: 3.7V\r\n</li><li>Voltage range: 4.2V~2.75V\r\n</li><li>Battery demensions: 18.23(D)*65.11(L)mm\r\n</li><li>Unit weight: 50g\r\n</li><li>Capacity density: 457Wh/L\r\n</li><li>Specific energy: 180Wh/Kg\r\n</li><li>Standred charging current: 1.1A (0.5C)\r\n</li><li>Standred discharge current: 1.1A (0.5C)\r\n</li><li>Max discharge current: 4.4A (2.0C)\r\n</li><li>Cycle life: 500T\r\n</li><li>Tempreture: -20\u00b0c~60\u00b0c\r\n</li><li>Certifications: CE, RoHS, UL\r\n</li></ul>\r\n<img src=\"https://lygte-info.dk/pic/Batteries2012/Staring%20IMR18650%202500mAh%20(Green)/Staring%20IMR18650%202500mAh%20(Green)-info.png\" border=\"0\" alt=\"Staring%20IMR18650%202500mAh%20(Green)-info\"><br>\r\n<br>\r\nThis is high current 18650 with fairly high capacity.<br>\r\n<br>\r\n<img src=\"https://lygte-info.dk/pic/Batteries2012/Staring%20IMR18650%202500mAh%20(Green)/DSC_6652.jpg\" border=\"0\" alt=\"DSC_6652\"> <img src=\"https://lygte-info.dk/pic/Batteries2012/Staring%20IMR18650%202500mAh%20(Green)/DSC_6653.jpg\" border=\"0\" alt=\"DSC_6653\"><br>\r\n<br>\r\n<img src=\"https://lygte-info.dk/pic/Batteries2012/Staring%20IMR18650%202500mAh%20(Green)/DSC_6655.jpg\" border=\"0\" alt=\"DSC_6655\"> <img src=\"https://lygte-info.dk/pic/Batteries2012/Staring%20IMR18650%202500mAh%20(Green)/DSC_6656.jpg\" border=\"0\" alt=\"DSC_6656\"><br>\r\n<br>\r\n<img src=\"https://lygte-info.dk/pic/Batteries2012/Staring%20IMR18650%202500mAh%20(Green)/DSC_6657.jpg\" border=\"0\" alt=\"DSC_6657\"><br>\r\n<img src=\"https://lygte-info.dk/pic/Batteries2012/Staring%20IMR18650%202500mAh%20(Green)/DSC_6658.jpg\" border=\"0\" alt=\"DSC_6658\"><br>\r\n<br>\r\n<img src=\"https://lygte-info.dk/pic/Batteries2012/Staring%20IMR18650%202500mAh%20(Green)/Staring%20IMR18650%202500mAh%20(Green)-Capacity.png\" border=\"0\" alt=\"Staring%20IMR18650%202500mAh%20(Green)-Capacity\"><br>\r\n<br>\r\nThe discharge curves tracks just about perfect and the batteries works well up to 20A, at 30A they are strained.<br>\r\n<br>\r\n<img src=\"https://lygte-info.dk/pic/Batteries2012/Staring%20IMR18650%202500mAh%20(Green)/Staring%20IMR18650%202500mAh%20(Green)-Temp-15.0.png\" border=\"0\" alt=\"Staring%20IMR18650%202500mAh%20(Green)-Temp-15.0\"><br>\r\n<br>\r\n<img src=\"https://lygte-info.dk/pic/Batteries2012/Staring%20IMR18650%202500mAh%20(Green)/Staring%20IMR18650%202500mAh%20(Green)-Temp-20.0.png\" border=\"0\" alt=\"Staring%20IMR18650%202500mAh%20(Green)-Temp-20.0\"><br>\r\n<br>\r\nThey gets fairly hot at 20A, but it is in the acceptable range.<br>\r\n<br>\r\n<img src=\"https://lygte-info.dk/pic/Batteries2012/Staring%20IMR18650%202500mAh%20(Green)/Staring%20IMR18650%202500mAh%20(Green)-Temp-30.0.png\" border=\"0\" alt=\"Staring%20IMR18650%202500mAh%20(Green)-Temp-30.0\"><br>\r\n<br>\r\nAt 30A I would have terminated on temperature if the discharge had lasted a few second more, i.e. they are too hot.<br>\r\n<br>\r\n<img src=\"https://lygte-info.dk/pic/Batteries2012/Staring%20IMR18650%202500mAh%20(Green)/Staring%20IMR18650%202500mAh%20(Green)-CapacityTimeHours.png\" border=\"0\" alt=\"Staring%20IMR18650%202500mAh%20(Green)-CapacityTimeHours\"><br>\r\n<br>\r\n<img src=\"https://lygte-info.dk/pic/Batteries2012/Staring%20IMR18650%202500mAh%20(Green)/Staring%20IMR18650%202500mAh%20(Green)-CapacityTime.png\" border=\"0\" alt=\"Staring%20IMR18650%202500mAh%20(Green)-CapacityTime\"><br>\r\n<br>\r\n<img src=\"https://lygte-info.dk/pic/Batteries2012/Staring%20IMR18650%202500mAh%20(Green)/Staring%20IMR18650%202500mAh%20(Green)-Energy.png\" border=\"0\" alt=\"Staring%20IMR18650%202500mAh%20(Green)-Energy\"><br>\r\n<br>\r\n<img src=\"https://lygte-info.dk/pic/Batteries2012/Staring%20IMR18650%202500mAh%20(Green)/Staring%20IMR18650%202500mAh%20(Green)-PowerLoadTime.png\" border=\"0\" alt=\"Staring%20IMR18650%202500mAh%20(Green)-PowerLoadTime\"><br>\r\n<br>\r\n<img src=\"https://lygte-info.dk/pic/Batteries2012/Staring%20IMR18650%202500mAh%20(Green)/Staring%20IMR18650%202500mAh%20(Green)-TripCurrent.png\" border=\"0\" alt=\"Staring%20IMR18650%202500mAh%20(Green)-TripCurrent\"><br>\r\n<br>\r\n<img src=\"https://lygte-info.dk/pic/Batteries2012/Staring%20IMR18650%202500mAh%20(Green)/Staring%20IMR18650%202500mAh%20(Green)-Charge.png\" border=\"0\" alt=\"Staring%20IMR18650%202500mAh%20(Green)-Charge\"><br>\r\n<br>\r\n<br>\r\n<br>\r\n<span style=\"font-size:25px;\">Conclusion</span><br>\r\n<br>\r\nThe cells has very good performance up to 20A continuous.<br>\r\n<br>\r\n<br>\r\n<br>\r\n<span style=\"font-size:25px;\">Notes and links</span><br>\r\n<br>\r\nThe batteries was supplied by Staring for a review.<br>\r\n<br>\r\n<a href=\"https://lygte-info.dk/info/Batteries2012Info%20UK.html\">How is the test done and how to read the charts</a><br>\r\n<a href=\"https://lygte-info.dk/info/battery%20protection%20UK.html\">How is a protected LiIon battery constructed</a><br>\r\n<a href=\"https://lygte-info.dk/info/Battery%20button%20or%20flat%20UK.html\">More about button top and flat top batteries</a><br>\r\n<a href=\"https://lygte-info.dk/review/batteries2012/Common18650comparator.php\">Compare to 18650 and other batteries</a><br>\r\n</body>",
  "url": "https://lygte-info.dk/review/batteries2012/Staring IMR18650 2500mAh (Green) UK.html",
  "title": "Staring IMR18650 2500mAh (Green)",
  "slug": "staring-imr18650-2500mah-green",
  "battery_type": "LiIon",
  "top": "flat",
  "rated_mah": 2500,
  "prot": "na",
  "year": "9-2016"
}