{
  "html": "<body style=\"background-color:#F0F8FF; font-family:Verdana, Arial, Helvetica, sans-serif; font-size:12; color:#000000; \">\r\n<span style=\"font-size:25px;\">Windyfire IMR16340 600mAh (Yellow)</span><br>\r\n<br>\r\n<br>\r\n<img src=\"https://lygte-info.dk/pic/Batteries2012Small/Windyfire%20IMR16340%20600mAh%20(Yellow)/DSC_2219.jpg\" border=\"0\" alt=\"DSC_2219\"><br>\r\n<br>\r\nOfficial specifications:<ul>\r\n<li>Capacity: 600mAh\r\n</li><li>Nominal voltage: 3.7V\r\n</li><li>Max. discharge current: 3A\r\n</li><li>Standard charge: 0.3A-0.75A/4.2V\r\n</li></ul>\r\n<img src=\"https://lygte-info.dk/pic/Batteries2012Small/Windyfire%20IMR16340%20600mAh%20(Yellow)/Windyfire%20IMR16340%20600mAh%20(Yellow)-info.png\" border=\"0\" alt=\"Windyfire%20IMR16340%20600mAh%20(Yellow)-info\"><br>\r\n<br>\r\nA high current 16340, in this size high current only means a few amps.<br>\r\n<br>\r\n<img src=\"https://lygte-info.dk/pic/Batteries2012Small/Windyfire%20IMR16340%20600mAh%20(Yellow)/DSC_2218.jpg\" border=\"0\" alt=\"DSC_2218\"><br>\r\n<br>\r\n<img src=\"https://lygte-info.dk/pic/Batteries2012Small/Windyfire%20IMR16340%20600mAh%20(Yellow)/DSC_2220.jpg\" border=\"0\" alt=\"DSC_2220\"> <img src=\"https://lygte-info.dk/pic/Batteries2012Small/Windyfire%20IMR16340%20600mAh%20(Yellow)/DSC_2221.jpg\" border=\"0\" alt=\"DSC_2221\"><br>\r\n<br>\r\n<img src=\"https://lygte-info.dk/pic/Batteries2012Small/Windyfire%20IMR16340%20600mAh%20(Yellow)/DSC_2222.jpg\" border=\"0\" alt=\"DSC_2222\"><br>\r\n<img src=\"https://lygte-info.dk/pic/Batteries2012Small/Windyfire%20IMR16340%20600mAh%20(Yellow)/DSC_2223.jpg\" border=\"0\" alt=\"DSC_2223\"><br>\r\n<br>\r\n<img src=\"https://lygte-info.dk/pic/Batteries2012Small/Windyfire%20IMR16340%20600mAh%20(Yellow)/Windyfire%20IMR16340%20600mAh%20(Yellow)-Capacity.png\" border=\"0\" alt=\"Windyfire%20IMR16340%20600mAh%20(Yellow)-Capacity\"><br>\r\n<br>\r\nThe two cells has fairly good tracking and the 3A rating looks very resonable.<br>\r\n<br>\r\n<img src=\"https://lygte-info.dk/pic/Batteries2012Small/Windyfire%20IMR16340%20600mAh%20(Yellow)/Windyfire%20IMR16340%20600mAh%20(Yellow)-CapacityTimeHours.png\" border=\"0\" alt=\"Windyfire%20IMR16340%20600mAh%20(Yellow)-CapacityTimeHours\"><br>\r\n<br>\r\n<img src=\"https://lygte-info.dk/pic/Batteries2012Small/Windyfire%20IMR16340%20600mAh%20(Yellow)/Windyfire%20IMR16340%20600mAh%20(Yellow)-CapacityTime.png\" border=\"0\" alt=\"Windyfire%20IMR16340%20600mAh%20(Yellow)-CapacityTime\"><br>\r\n<br>\r\n<img src=\"https://lygte-info.dk/pic/Batteries2012Small/Windyfire%20IMR16340%20600mAh%20(Yellow)/Windyfire%20IMR16340%20600mAh%20(Yellow)-Energy.png\" border=\"0\" alt=\"Windyfire%20IMR16340%20600mAh%20(Yellow)-Energy\"><br>\r\n<br>\r\n<img src=\"https://lygte-info.dk/pic/Batteries2012Small/Windyfire%20IMR16340%20600mAh%20(Yellow)/Windyfire%20IMR16340%20600mAh%20(Yellow)-PowerLoadTime.png\" border=\"0\" alt=\"Windyfire%20IMR16340%20600mAh%20(Yellow)-PowerLoadTime\"><br>\r\n<br>\r\n<img src=\"https://lygte-info.dk/pic/Batteries2012Small/Windyfire%20IMR16340%20600mAh%20(Yellow)/Windyfire%20IMR16340%20600mAh%20(Yellow)-TripCurrent.png\" border=\"0\" alt=\"Windyfire%20IMR16340%20600mAh%20(Yellow)-TripCurrent\"><br>\r\n<br>\r\n<img src=\"https://lygte-info.dk/pic/Batteries2012Small/Windyfire%20IMR16340%20600mAh%20(Yellow)/Windyfire%20IMR16340%20600mAh%20(Yellow)-Charge.png\" border=\"0\" alt=\"Windyfire%20IMR16340%20600mAh%20(Yellow)-Charge\"><br>\r\n<br>\r\n<br>\r\n<br>\r\n<span style=\"font-size:25px;\">Conclusion</span><br>\r\n<br>\r\nThe combination of capacity and current ability look good in this cell.<br>\r\n<br>\r\n<br>\r\n<br>\r\n<span style=\"font-size:25px;\">Notes and links</span><br>\r\n<br>\r\nThe batteries was supplied by Windyfire for review.<br>\r\n<br>\r\n<a href=\"https://lygte-info.dk/info/Batteries2012Info%20UK.html\">How is the test done and how to read the charts</a><br>\r\n<a href=\"https://lygte-info.dk/info/battery%20protection%20UK.html\">How is a protected LiIon battery constructed</a><br>\r\n<a href=\"https://lygte-info.dk/info/Battery%20button%20or%20flat%20UK.html\">More about button top and flat top batteries</a><br>\r\n<a href=\"https://lygte-info.dk/review/batteries2012/CommonSmallSummary%20UK.html\">Comparison to other LiIon batteries</a><br>\r\n</body>",
  "_id": "windyfire-imr16340-600mah-yellow",
  "url": "https://lygte-info.dk/review/batteries2012/Windyfire IMR16340 600mAh (Yellow) UK.html",
  "title": "Windyfire IMR16340 600mAh (Yellow)",
  "slug": "windyfire-imr16340-600mah-yellow",
  "type": "LiIon",
  "size": "16340",
  "top": "flat",
  "rated_mah": 500,
  "prot": "na",
  "year": 2015,
  "preview": "https://lygte-info.dk/pic/Batteries2012Small/Windyfire%20IMR16340%20600mAh%20(Yellow)/DSC_2219.jpg"
}